{
  "version": "rf_BTCUSDT_v20260328_0406",
  "symbol": "BTC/USDT",
  "model_type": "rf",
  "timeframe": "5m",
  "features": [
    "rsi_14",
    "macd_norm",
    "macd_signal_norm",
    "macd_hist_norm",
    "atr_norm",
    "bb_position",
    "bb_width",
    "adx",
    "ema_20_slope",
    "ema_50_slope",
    "ema_cross",
    "return_1",
    "return_3",
    "return_5",
    "volatility_10",
    "candle_body",
    "candle_shadow",
    "volume_ratio"
  ],
  "metrics": {
    "accuracy": 0.6119,
    "precision": 0.2303,
    "recall": 0.4053,
    "f1": 0.2938,
    "roc_auc": 0.5786
  },
  "trained_at": "2026-03-28T04:06:58.310001+00:00"
}